algospackage.py
algotools.py
algotoolsshiridi-0.0.9.dist-info/METADATA
algotoolsshiridi-0.0.9.dist-info/WHEEL
algotoolsshiridi-0.0.9.dist-info/top_level.txt
algotoolsshiridi-0.0.9.dist-info/RECORD
