Metadata-Version: 2.1
Name: algotoolsshiridi
Version: 0.0.9
Summary: A one stop solution for solving your required algorithms
Home-page: UNKNOWN
Author: UNKNOWN
Author-email: shiridikumarpeddinti836@gmail.com
License: UNKNOWN
Platform: UNKNOWN
Requires-Dist: matplotlib
Requires-Dist: pandas
Requires-Dist: numpy
Requires-Dist: seaborn
